microeval/__init__.py
microeval/chat.py
microeval/cli.py
microeval/evaluator.py
microeval/graph.py
microeval/index.html
microeval/llm.py
microeval/logger.py
microeval/runner.py
microeval/schemas.py
microeval/server.py
microeval/yamlx.py
microeval/json-evals/prompts/candidate-skills.txt
microeval/json-evals/queries/engineer.yaml
microeval/json-evals/runs/engineer-bedrock-nova-pro.yaml
microeval/json-evals/runs/engineer-groq-llama-3.3-70b.yaml
microeval/json-evals/runs/engineer-ollama-llama3.2.yaml
microeval/json-evals/runs/engineer-openai-gpt-4o.yaml
microeval/summary-evals/prompts/summarize.txt
microeval/summary-evals/queries/summarize.yaml
microeval/summary-evals/runs/summarize-bedrock-nova.yaml
microeval/summary-evals/runs/summarize-groq-llama.yaml
microeval/summary-evals/runs/summarize-ollama-llama3.yaml
microeval/summary-evals/runs/summarize-openai-gpt-4o.yaml
microeval-0.1.5.dist-info/METADATA
microeval-0.1.5.dist-info/WHEEL
microeval-0.1.5.dist-info/entry_points.txt
microeval-0.1.5.dist-info/licenses/LICENSE
microeval-0.1.5.dist-info/RECORD
