Metadata-Version: 2.4
Name: microeval
Version: 0.1.5
Summary: Minimal evaluation framework for LLM testing with local and cloud providers
Project-URL: Homepage, https://github.com/boscoh/microeval
Project-URL: Repository, https://github.com/boscoh/microeval
Author-email: Bosco Ho <boscoh@gmail.com>
License: MIT
License-File: LICENSE
Keywords: aws,bedrock,evaluation,groq,llm,ollama,openai,testing
Classifier: Development Status :: 3 - Alpha
Classifier: Intended Audience :: Developers
Classifier: License :: OSI Approved :: MIT License
Classifier: Programming Language :: Python :: 3
Classifier: Programming Language :: Python :: 3.13
Classifier: Topic :: Scientific/Engineering :: Artificial Intelligence
Classifier: Topic :: Software Development :: Libraries :: Python Modules
Requires-Python: >=3.13
Requires-Dist: aioboto3>=15.2.0
Requires-Dist: boto3>=1.35.0
Requires-Dist: cyclopts>=0.6.0
Requires-Dist: fastapi>=0.116.1
Requires-Dist: groq>=0.14.0
Requires-Dist: httpx>=0.28.1
Requires-Dist: ollama>=0.5.1
Requires-Dist: openai>=1.0.0
Requires-Dist: path>=17.1.0
Requires-Dist: python-dotenv>=1.0.1
Requires-Dist: pyyaml>=6.0.2
Requires-Dist: rich>=14.1.0
Requires-Dist: ty>=0.0.4
Requires-Dist: uvicorn>=0.35.0
